[
  {
    "firstName": "Marcos",
    "lastName": "Pascual",
    "email": "marcos.pascual@example.com",
    "username": "smallpanda110",
    "password": "bartman",
    "invokedAt": "2021-08-17T00:00:46.448Z"
  },
  {
    "firstName": "Ivete",
    "lastName": "Farias",
    "email": "ivete.farias@example.com",
    "username": "angrydog956",
    "password": "amelia",
    "invokedAt": "2021-08-17T01:21:08.298Z"
  },
  {
    "firstName": "Nurdan",
    "lastName": "Candan",
    "email": "nurdan.candan@example.com",
    "username": "happymouse909",
    "password": "magician",
    "invokedAt": "2021-08-17T02:09:38.103Z"
  }
]