[
  {
    "firstName": "Océane",
    "lastName": "Lefevre",
    "email": "oceane.lefevre@example.com",
    "username": "brownpeacock615",
    "password": "biao",
    "invokedAt": "2021-01-22T00:29:05.658Z"
  },
  {
    "firstName": "Mel",
    "lastName": "Teixeira",
    "email": "mel.teixeira@example.com",
    "username": "organicrabbit154",
    "password": "browning",
    "invokedAt": "2021-01-22T02:34:07.098Z"
  },
  {
    "firstName": "Nurdan",
    "lastName": "Hegge",
    "email": "nurdan.hegge@example.com",
    "username": "ticklishostrich164",
    "password": "gadget",
    "invokedAt": "2021-01-22T03:49:52.541Z"
  },
  {
    "firstName": "Koen",
    "lastName": "Demandt",
    "email": "koen.demandt@example.com",
    "username": "orangedog555",
    "password": "dragoon",
    "invokedAt": "2021-01-22T04:27:13.292Z"
  },
  {
    "firstName": "Karen",
    "lastName": "Klavenes",
    "email": "karen.klavenes@example.com",
    "username": "yellowbird939",
    "password": "pitchers",
    "invokedAt": "2021-01-22T05:35:48.572Z"
  },
  {
    "firstName": "Elsa",
    "lastName": "Makela",
    "email": "elsa.makela@example.com",
    "username": "crazybutterfly654",
    "password": "jameson",
    "invokedAt": "2021-01-22T06:25:42.273Z"
  },
  {
    "firstName": "Delphine",
    "lastName": "Mackay",
    "email": "delphine.mackay@example.com",
    "username": "purplelion556",
    "password": "bruce1",
    "invokedAt": "2021-01-22T07:32:35.420Z"
  },
  {
    "firstName": "Sebastian",
    "lastName": "Gutierrez",
    "email": "sebastian.gutierrez@example.com",
    "username": "orangefrog527",
    "password": "brett",
    "invokedAt": "2021-01-22T08:24:46.388Z"
  },
  {
    "firstName": "Stephen",
    "lastName": "Franklin",
    "email": "stephen.franklin@example.com",
    "username": "orangeleopard804",
    "password": "eagle",
    "invokedAt": "2021-01-22T09:32:17.617Z"
  },
  {
    "firstName": "Jordan",
    "lastName": "Dupuis",
    "email": "jordan.dupuis@example.com",
    "username": "organicpanda544",
    "password": "surf",
    "invokedAt": "2021-01-22T10:33:29.263Z"
  },
  {
    "firstName": "Tracey",
    "lastName": "Houweling",
    "email": "tracey.houweling@example.com",
    "username": "purplewolf388",
    "password": "letmein",
    "invokedAt": "2021-01-22T11:32:10.870Z"
  },
  {
    "firstName": "Aleida",
    "lastName": "Zwarts",
    "email": "aleida.zwarts@example.com",
    "username": "bluefish767",
    "password": "carmen",
    "invokedAt": "2021-01-22T12:18:13.766Z"
  }
]