[
  {
    "firstName": "Suzanna",
    "lastName": "Lawrence",
    "email": "suzanna.lawrence@example.com",
    "username": "blackfish821",
    "password": "doubled",
    "invokedAt": "2021-11-30T00:00:59.011Z"
  },
  {
    "firstName": "Andreas",
    "lastName": "Petersen",
    "email": "andreas.petersen@example.com",
    "username": "greenduck220",
    "password": "nellie",
    "invokedAt": "2021-11-30T01:20:41.563Z"
  },
  {
    "firstName": "Kaylee",
    "lastName": "Hudson",
    "email": "kaylee.hudson@example.com",
    "username": "tinylion764",
    "password": "mouse1",
    "invokedAt": "2021-11-30T02:05:34.876Z"
  },
  {
    "firstName": "Barb",
    "lastName": "Mills",
    "email": "barb.mills@example.com",
    "username": "silverbird693",
    "password": "presario",
    "invokedAt": "2021-11-30T03:00:45.215Z"
  },
  {
    "firstName": "Rafael",
    "lastName": "Hartviksen",
    "email": "rafael.hartviksen@example.com",
    "username": "angrycat149",
    "password": "double",
    "invokedAt": "2021-11-30T04:00:52.165Z"
  },
  {
    "firstName": "Valentin",
    "lastName": "Giraud",
    "email": "valentin.giraud@example.com",
    "username": "brownmeercat569",
    "password": "gizmodo",
    "invokedAt": "2021-11-30T05:00:43.338Z"
  },
  {
    "firstName": "Jose",
    "lastName": "Montgomery",
    "email": "jose.montgomery@example.com",
    "username": "orangewolf307",
    "password": "bertie",
    "invokedAt": "2021-11-30T06:00:34.943Z"
  },
  {
    "firstName": "Emma",
    "lastName": "Li",
    "email": "emma.li@example.com",
    "username": "crazyrabbit580",
    "password": "lesley",
    "invokedAt": "2021-11-30T07:00:36.507Z"
  },
  {
    "firstName": "Brianna",
    "lastName": "Sullivan",
    "email": "brianna.sullivan@example.com",
    "username": "sadmeercat941",
    "password": "possum",
    "invokedAt": "2021-11-30T08:00:54.023Z"
  }
]