[
  {
    "firstName": "Harper",
    "lastName": "Smith",
    "email": "harper.smith@example.com",
    "username": "tinylion583",
    "password": "weed",
    "invokedAt": "2022-04-21T00:00:56.688Z"
  },
  {
    "firstName": "Traute",
    "lastName": "Freiberg",
    "email": "traute.freiberg@example.com",
    "username": "smallwolf541",
    "password": "1974",
    "invokedAt": "2022-04-21T01:29:28.448Z"
  },
  {
    "firstName": "Helma",
    "lastName": "Zellner",
    "email": "helma.zellner@example.com",
    "username": "brownpanda689",
    "password": "swingers",
    "invokedAt": "2022-04-21T02:39:10.619Z"
  },
  {
    "firstName": "Arcanjo",
    "lastName": "da Cunha",
    "email": "arcanjo.dacunha@example.com",
    "username": "crazyelephant897",
    "password": "skyler",
    "invokedAt": "2022-04-21T03:28:23.725Z"
  }
]