[
  {
    "firstName": "سینا",
    "lastName": "احمدی",
    "email": "syn.hmdy@example.com",
    "username": "happylion258",
    "password": "353535",
    "invokedAt": "2022-11-01T00:00:53.591Z"
  },
  {
    "firstName": "Josefine",
    "lastName": "Larsen",
    "email": "josefine.larsen@example.com",
    "username": "angryladybug175",
    "password": "kittys",
    "invokedAt": "2022-11-01T01:28:54.330Z"
  },
  {
    "firstName": "Benjamin",
    "lastName": "Bishop",
    "email": "benjamin.bishop@example.com",
    "username": "biggoose414",
    "password": "manson",
    "invokedAt": "2022-11-01T02:53:13.268Z"
  },
  {
    "firstName": "Bently",
    "lastName": "Wilson",
    "email": "bently.wilson@example.com",
    "username": "organicbutterfly552",
    "password": "show",
    "invokedAt": "2022-11-01T03:44:29.230Z"
  },
  {
    "firstName": "Luis",
    "lastName": "Cortes",
    "email": "luis.cortes@example.com",
    "username": "redduck736",
    "password": "lewis",
    "invokedAt": "2022-11-01T04:28:01.627Z"
  },
  {
    "firstName": "Cameron",
    "lastName": "Wang",
    "email": "cameron.wang@example.com",
    "username": "silverbutterfly357",
    "password": "barbie",
    "invokedAt": "2022-11-01T05:22:16.345Z"
  },
  {
    "firstName": "Fernando",
    "lastName": "Olson",
    "email": "fernando.olson@example.com",
    "username": "redlion253",
    "password": "banane",
    "invokedAt": "2022-11-01T06:05:41.581Z"
  }
]