[
  {
    "firstName": "Flora",
    "lastName": "Nicolas",
    "email": "flora.nicolas@example.com",
    "username": "ticklishbutterfly541",
    "password": "stinker",
    "invokedAt": "2022-03-11T00:01:00.362Z"
  },
  {
    "firstName": "محمدپارسا",
    "lastName": "قاسمی",
    "email": "mhmdprs.qsmy@example.com",
    "username": "redelephant457",
    "password": "heat",
    "invokedAt": "2022-03-11T01:26:53.033Z"
  },
  {
    "firstName": "Daniel",
    "lastName": "Jensen",
    "email": "daniel.jensen@example.com",
    "username": "smallleopard806",
    "password": "delete",
    "invokedAt": "2022-03-11T02:21:44.938Z"
  },
  {
    "firstName": "Eva",
    "lastName": "Vargas",
    "email": "eva.vargas@example.com",
    "username": "yellowlion758",
    "password": "london",
    "invokedAt": "2022-03-11T03:02:13.172Z"
  },
  {
    "firstName": "Tim",
    "lastName": "Bailey",
    "email": "tim.bailey@example.com",
    "username": "sadlion357",
    "password": "qweqwe",
    "invokedAt": "2022-03-11T04:00:57.560Z"
  },
  {
    "firstName": "Troy",
    "lastName": "Mills",
    "email": "troy.mills@example.com",
    "username": "happyelephant916",
    "password": "joker1",
    "invokedAt": "2022-03-11T05:00:42.109Z"
  },
  {
    "firstName": "Lida",
    "lastName": "Sales",
    "email": "lida.sales@example.com",
    "username": "yellowpanda915",
    "password": "blossom",
    "invokedAt": "2022-03-11T06:00:52.628Z"
  },
  {
    "firstName": "Ellen",
    "lastName": "Aho",
    "email": "ellen.aho@example.com",
    "username": "purplezebra534",
    "password": "pelican",
    "invokedAt": "2022-03-11T07:00:39.697Z"
  },
  {
    "firstName": "Greta",
    "lastName": "Reinecke",
    "email": "greta.reinecke@example.com",
    "username": "happymeercat998",
    "password": "clyde",
    "invokedAt": "2022-03-11T08:00:51.893Z"
  },
  {
    "firstName": "Adam",
    "lastName": "Côté",
    "email": "adam.cote@example.com",
    "username": "purplepeacock579",
    "password": "spiderma",
    "invokedAt": "2022-03-11T09:00:33.659Z"
  },
  {
    "firstName": "Alvar",
    "lastName": "Wathne",
    "email": "alvar.wathne@example.com",
    "username": "goldenlion491",
    "password": "jimmie",
    "invokedAt": "2022-03-11T10:02:32.197Z"
  },
  {
    "firstName": "Freya",
    "lastName": "Taylor",
    "email": "freya.taylor@example.com",
    "username": "angryrabbit930",
    "password": "line",
    "invokedAt": "2022-03-11T11:00:50.514Z"
  },
  {
    "firstName": "Martin",
    "lastName": "Wheeler",
    "email": "martin.wheeler@example.com",
    "username": "happygoose724",
    "password": "johnson1",
    "invokedAt": "2022-03-11T12:00:56.482Z"
  },
  {
    "firstName": "پرهام",
    "lastName": "گلشن",
    "email": "prhm.glshn@example.com",
    "username": "blueswan345",
    "password": "1000",
    "invokedAt": "2022-03-11T13:04:37.701Z"
  },
  {
    "firstName": "Lucy",
    "lastName": "Patel",
    "email": "lucy.patel@example.com",
    "username": "brownelephant850",
    "password": "hunt",
    "invokedAt": "2022-03-11T14:00:50.227Z"
  },
  {
    "firstName": "Lily",
    "lastName": "David",
    "email": "lily.david@example.com",
    "username": "silverwolf156",
    "password": "helium",
    "invokedAt": "2022-03-11T15:05:50.621Z"
  },
  {
    "firstName": "Roger",
    "lastName": "Perez",
    "email": "roger.perez@example.com",
    "username": "heavymouse614",
    "password": "billy1",
    "invokedAt": "2022-03-11T16:01:04.390Z"
  },
  {
    "firstName": "Shane",
    "lastName": "Carpenter",
    "email": "shane.carpenter@example.com",
    "username": "happyfish255",
    "password": "rated",
    "invokedAt": "2022-03-11T17:03:12.930Z"
  },
  {
    "firstName": "Silke",
    "lastName": "Christensen",
    "email": "silke.christensen@example.com",
    "username": "yellowelephant793",
    "password": "baker",
    "invokedAt": "2022-03-11T18:00:54.385Z"
  },
  {
    "firstName": "Andreas",
    "lastName": "Pedersen",
    "email": "andreas.pedersen@example.com",
    "username": "tinykoala702",
    "password": "dirty",
    "invokedAt": "2022-03-11T19:00:33.335Z"
  },
  {
    "firstName": "Amalia",
    "lastName": "Lecomte",
    "email": "amalia.lecomte@example.com",
    "username": "redostrich138",
    "password": "fmale",
    "invokedAt": "2022-03-11T20:00:35.841Z"
  },
  {
    "firstName": "Louane",
    "lastName": "Berger",
    "email": "louane.berger@example.com",
    "username": "orangewolf736",
    "password": "quest",
    "invokedAt": "2022-03-11T21:00:48.598Z"
  },
  {
    "firstName": "كيان",
    "lastName": "کامروا",
    "email": "kyn.khmrw@example.com",
    "username": "whiterabbit225",
    "password": "gman",
    "invokedAt": "2022-03-11T22:00:50.046Z"
  },
  {
    "firstName": "Sanni",
    "lastName": "Hietala",
    "email": "sanni.hietala@example.com",
    "username": "greenzebra659",
    "password": "dingle",
    "invokedAt": "2022-03-11T23:00:51.830Z"
  }
]