[
  {
    "firstName": "Kerim",
    "lastName": "Akyürek",
    "email": "kerim.akyurek@example.com",
    "username": "yellowfrog215",
    "password": "bigd",
    "invokedAt": "2022-03-17T00:00:57.178Z"
  },
  {
    "firstName": "Olivia",
    "lastName": "Murray",
    "email": "olivia.murray@example.com",
    "username": "heavydog502",
    "password": "tree",
    "invokedAt": "2022-03-17T01:26:54.403Z"
  },
  {
    "firstName": "Albert",
    "lastName": "Cook",
    "email": "albert.cook@example.com",
    "username": "orangedog308",
    "password": "shower",
    "invokedAt": "2022-03-17T02:22:00.340Z"
  },
  {
    "firstName": "Lambert",
    "lastName": "Grünberg",
    "email": "lambert.grunberg@example.com",
    "username": "silvergoose137",
    "password": "ambrose",
    "invokedAt": "2022-03-17T03:01:39.363Z"
  },
  {
    "firstName": "Käthi",
    "lastName": "Dufour",
    "email": "kathi.dufour@example.com",
    "username": "beautifullion489",
    "password": "lorraine",
    "invokedAt": "2022-03-17T04:00:37.914Z"
  },
  {
    "firstName": "Nikolai",
    "lastName": "Lundgård",
    "email": "nikolai.lundgard@example.com",
    "username": "orangebear766",
    "password": "harald",
    "invokedAt": "2022-03-17T05:00:39.952Z"
  },
  {
    "firstName": "Ana",
    "lastName": "Gallego",
    "email": "ana.gallego@example.com",
    "username": "happygoose998",
    "password": "popo",
    "invokedAt": "2022-03-17T06:00:42.698Z"
  },
  {
    "firstName": "Darlene",
    "lastName": "Montgomery",
    "email": "darlene.montgomery@example.com",
    "username": "whitesnake679",
    "password": "1947",
    "invokedAt": "2022-03-17T07:00:41.063Z"
  },
  {
    "firstName": "Matteo",
    "lastName": "Lemaire",
    "email": "matteo.lemaire@example.com",
    "username": "angrygorilla512",
    "password": "2001",
    "invokedAt": "2022-03-17T08:00:56.102Z"
  },
  {
    "firstName": "Lucas",
    "lastName": "Nielsen",
    "email": "lucas.nielsen@example.com",
    "username": "beautifulfrog937",
    "password": "camper",
    "invokedAt": "2022-03-17T09:00:43.297Z"
  },
  {
    "firstName": "Debbie",
    "lastName": "Parker",
    "email": "debbie.parker@example.com",
    "username": "happygoose398",
    "password": "bart",
    "invokedAt": "2022-03-17T10:05:47.345Z"
  },
  {
    "firstName": "علی",
    "lastName": "پارسا",
    "email": "aaly.prs@example.com",
    "username": "orangezebra141",
    "password": "4wwvte",
    "invokedAt": "2022-03-17T11:05:43.181Z"
  },
  {
    "firstName": "Felix",
    "lastName": "Taylor",
    "email": "felix.taylor@example.com",
    "username": "whitebear708",
    "password": "castle",
    "invokedAt": "2022-03-17T12:00:57.643Z"
  },
  {
    "firstName": "Andres",
    "lastName": "Castillo",
    "email": "andres.castillo@example.com",
    "username": "tinyduck531",
    "password": "gladiator",
    "invokedAt": "2022-03-17T13:11:15.491Z"
  },
  {
    "firstName": "Nixon",
    "lastName": "Hughes",
    "email": "nixon.hughes@example.com",
    "username": "smallsnake949",
    "password": "ruby",
    "invokedAt": "2022-03-17T15:00:46.663Z"
  },
  {
    "firstName": "Maëly",
    "lastName": "Brun",
    "email": "maely.brun@example.com",
    "username": "angryfish730",
    "password": "garner",
    "invokedAt": "2022-03-17T16:05:47.008Z"
  },
  {
    "firstName": "Côme",
    "lastName": "Sanchez",
    "email": "come.sanchez@example.com",
    "username": "redtiger765",
    "password": "hamish",
    "invokedAt": "2022-03-17T17:02:44.836Z"
  },
  {
    "firstName": "Liam",
    "lastName": "Gagné",
    "email": "liam.gagne@example.com",
    "username": "ticklishfish267",
    "password": "honey",
    "invokedAt": "2022-03-17T18:02:22.885Z"
  },
  {
    "firstName": "Bartholomäus",
    "lastName": "Hilpert",
    "email": "bartholomaus.hilpert@example.com",
    "username": "beautifulgorilla870",
    "password": "poiu",
    "invokedAt": "2022-03-17T19:00:35.395Z"
  },
  {
    "firstName": "Susie",
    "lastName": "Simpson",
    "email": "susie.simpson@example.com",
    "username": "smallfish275",
    "password": "love",
    "invokedAt": "2022-03-17T20:00:48.970Z"
  },
  {
    "firstName": "Joona",
    "lastName": "Honkala",
    "email": "joona.honkala@example.com",
    "username": "browncat344",
    "password": "blanca",
    "invokedAt": "2022-03-17T21:00:41.158Z"
  },
  {
    "firstName": "Abigail",
    "lastName": "Beck",
    "email": "abigail.beck@example.com",
    "username": "tinyfish107",
    "password": "tomcat",
    "invokedAt": "2022-03-17T22:00:36.528Z"
  },
  {
    "firstName": "Philip",
    "lastName": "Jean-Baptiste",
    "email": "philip.jean-baptiste@example.com",
    "username": "angrycat828",
    "password": "hotrats",
    "invokedAt": "2022-03-17T23:01:51.202Z"
  }
]