[
  {
    "firstName": "Christian",
    "lastName": "Arias",
    "email": "christian.arias@example.com",
    "username": "bigelephant722",
    "password": "cayman",
    "invokedAt": "2023-09-30T00:00:25.180Z"
  },
  {
    "firstName": "پرنیا",
    "lastName": "پارسا",
    "email": "prny.prs@example.com",
    "username": "ticklishbird386",
    "password": "beng",
    "invokedAt": "2023-09-30T01:20:29.582Z"
  },
  {
    "firstName": "Gianluca",
    "lastName": "Haanen",
    "email": "gianluca.haanen@example.com",
    "username": "organicrabbit280",
    "password": "carmen",
    "invokedAt": "2023-09-30T02:05:15.448Z"
  },
  {
    "firstName": "Albane",
    "lastName": "Mercier",
    "email": "albane.mercier@example.com",
    "username": "orangekoala980",
    "password": "zaq123",
    "invokedAt": "2023-09-30T03:00:22.674Z"
  },
  {
    "firstName": "میلاد",
    "lastName": "كامياران",
    "email": "myld.kmyrn@example.com",
    "username": "orangegoose714",
    "password": "yyyyyyy",
    "invokedAt": "2023-09-30T04:00:35.199Z"
  },
  {
    "firstName": "Donna",
    "lastName": "Zerov",
    "email": "donna.zerov@example.com",
    "username": "lazytiger154",
    "password": "polly",
    "invokedAt": "2023-09-30T05:00:22.734Z"
  },
  {
    "firstName": "Efe",
    "lastName": "Öztürk",
    "email": "efe.ozturk@example.com",
    "username": "greenpanda879",
    "password": "moneyman",
    "invokedAt": "2023-09-30T06:00:30.280Z"
  },
  {
    "firstName": "Mudrolyuba",
    "lastName": "Galaychuk",
    "email": "mudrolyuba.galaychuk@example.com",
    "username": "lazymouse379",
    "password": "transam",
    "invokedAt": "2023-09-30T07:00:26.810Z"
  },
  {
    "firstName": "Karl-Ernst",
    "lastName": "Mann",
    "email": "karl-ernst.mann@example.com",
    "username": "blacktiger992",
    "password": "kitten",
    "invokedAt": "2023-09-30T08:00:24.808Z"
  },
  {
    "firstName": "Jacobo",
    "lastName": "Saiz",
    "email": "jacobo.saiz@example.com",
    "username": "organicostrich146",
    "password": "cosworth",
    "invokedAt": "2023-09-30T09:00:23.822Z"
  },
  {
    "firstName": "Emma",
    "lastName": "Williams",
    "email": "emma.williams@example.com",
    "username": "blackmouse739",
    "password": "delmar",
    "invokedAt": "2023-09-30T10:00:19.733Z"
  },
  {
    "firstName": "Charlie",
    "lastName": "Wood",
    "email": "charlie.wood@example.com",
    "username": "organicostrich201",
    "password": "saleen",
    "invokedAt": "2023-09-30T11:00:20.877Z"
  },
  {
    "firstName": "Patrick",
    "lastName": "Porter",
    "email": "patrick.porter@example.com",
    "username": "angryfrog843",
    "password": "ffffffff",
    "invokedAt": "2023-09-30T12:00:21.577Z"
  },
  {
    "firstName": "Áureo",
    "lastName": "Pereira",
    "email": "aureo.pereira@example.com",
    "username": "yellowkoala770",
    "password": "portland",
    "invokedAt": "2023-09-30T13:00:34.522Z"
  },
  {
    "firstName": "Marceau",
    "lastName": "Faure",
    "email": "marceau.faure@example.com",
    "username": "tinypeacock902",
    "password": "shazam",
    "invokedAt": "2023-09-30T14:00:25.680Z"
  },
  {
    "firstName": "Noah",
    "lastName": "Morel",
    "email": "noah.morel@example.com",
    "username": "bluegorilla187",
    "password": "toon",
    "invokedAt": "2023-09-30T15:00:24.506Z"
  },
  {
    "firstName": "Miguel",
    "lastName": "Jenkins",
    "email": "miguel.jenkins@example.com",
    "username": "goldenbutterfly421",
    "password": "nascar",
    "invokedAt": "2023-09-30T16:00:23.497Z"
  },
  {
    "firstName": "Susanna",
    "lastName": "Thomas",
    "email": "susanna.thomas@example.com",
    "username": "whitedog784",
    "password": "baggio",
    "invokedAt": "2023-09-30T17:00:21.722Z"
  },
  {
    "firstName": "Kate",
    "lastName": "Anderson",
    "email": "kate.anderson@example.com",
    "username": "heavygoose793",
    "password": "scooter",
    "invokedAt": "2023-09-30T18:00:30.326Z"
  }
]