[
  {
    "firstName": "Patricia",
    "lastName": "Smythe",
    "email": "patricia.smythe@example.com",
    "username": "angryfish394",
    "password": "pa55word",
    "invokedAt": "2023-04-19T00:00:44.969Z"
  },
  {
    "firstName": "Vilina",
    "lastName": "Polyuga",
    "email": "vilina.polyuga@example.com",
    "username": "happyelephant860",
    "password": "musashi",
    "invokedAt": "2023-04-19T01:27:04.935Z"
  },
  {
    "firstName": "Topias",
    "lastName": "Kalas",
    "email": "topias.kalas@example.com",
    "username": "lazymouse206",
    "password": "tetsuo",
    "invokedAt": "2023-04-19T02:15:16.317Z"
  }
]