[
  {
    "firstName": "آراد",
    "lastName": "جعفری",
    "email": "ard.jaafry@example.com",
    "username": "silverzebra981",
    "password": "sultan",
    "invokedAt": "2023-06-03T00:01:07.509Z"
  },
  {
    "firstName": "Sedef",
    "lastName": "Mertoğlu",
    "email": "sedef.mertoglu@example.com",
    "username": "smallpanda856",
    "password": "jackpot",
    "invokedAt": "2023-06-03T01:28:00.396Z"
  },
  {
    "firstName": "Kenan",
    "lastName": "Sözeri",
    "email": "kenan.sozeri@example.com",
    "username": "brownrabbit241",
    "password": "ollie",
    "invokedAt": "2023-06-03T02:23:41.496Z"
  },
  {
    "firstName": "Carmelo",
    "lastName": "Durand",
    "email": "carmelo.durand@example.com",
    "username": "brownmeercat559",
    "password": "grunt",
    "invokedAt": "2023-06-03T03:00:45.342Z"
  },
  {
    "firstName": "Jorge",
    "lastName": "Ramos",
    "email": "jorge.ramos@example.com",
    "username": "smallswan321",
    "password": "mone",
    "invokedAt": "2023-06-03T04:00:42.798Z"
  },
  {
    "firstName": "Yatan",
    "lastName": "Chatterjee",
    "email": "yatan.chatterjee@example.com",
    "username": "bluepanda962",
    "password": "paramedi",
    "invokedAt": "2023-06-03T05:00:43.018Z"
  },
  {
    "firstName": "Isabella",
    "lastName": "Claire",
    "email": "isabella.claire@example.com",
    "username": "goldenfish856",
    "password": "foobar",
    "invokedAt": "2023-06-03T06:00:46.348Z"
  },
  {
    "firstName": "Mercedes",
    "lastName": "Alcaraz",
    "email": "mercedes.alcaraz@example.com",
    "username": "beautifulgoose783",
    "password": "redeye",
    "invokedAt": "2023-06-03T07:00:42.069Z"
  },
  {
    "firstName": "Thale",
    "lastName": "Fossen",
    "email": "thale.fossen@example.com",
    "username": "happyrabbit228",
    "password": "laurent",
    "invokedAt": "2023-06-03T08:00:51.056Z"
  },
  {
    "firstName": "Gema",
    "lastName": "Suarez",
    "email": "gema.suarez@example.com",
    "username": "tinypeacock484",
    "password": "birgit",
    "invokedAt": "2023-06-03T09:00:32.772Z"
  },
  {
    "firstName": "Ivanka",
    "lastName": "Engelmann",
    "email": "ivanka.engelmann@example.com",
    "username": "blackmouse793",
    "password": "funstuff",
    "invokedAt": "2023-06-03T10:00:43.258Z"
  },
  {
    "firstName": "Vicky",
    "lastName": "Nelson",
    "email": "vicky.nelson@example.com",
    "username": "silverduck656",
    "password": "firefly",
    "invokedAt": "2023-06-03T11:00:40.770Z"
  },
  {
    "firstName": "Kathrin",
    "lastName": "Joly",
    "email": "kathrin.joly@example.com",
    "username": "beautifulfish444",
    "password": "alexia",
    "invokedAt": "2023-06-03T12:01:02.976Z"
  },
  {
    "firstName": "Jovica",
    "lastName": "Sekulić",
    "email": "jovica.sekulic@example.com",
    "username": "yellowfrog703",
    "password": "fallon",
    "invokedAt": "2023-06-03T13:01:21.517Z"
  },
  {
    "firstName": "Rubén",
    "lastName": "Guevara",
    "email": "ruben.guevara@example.com",
    "username": "yellowostrich399",
    "password": "peaches1",
    "invokedAt": "2023-06-03T14:00:43.138Z"
  },
  {
    "firstName": "Cathleen",
    "lastName": "Reichenbach",
    "email": "cathleen.reichenbach@example.com",
    "username": "greenlion984",
    "password": "portugal",
    "invokedAt": "2023-06-03T15:00:37.718Z"
  },
  {
    "firstName": "Alexandra",
    "lastName": "Brunet",
    "email": "alexandra.brunet@example.com",
    "username": "biggoose575",
    "password": "joshua",
    "invokedAt": "2023-06-03T16:00:41.236Z"
  },
  {
    "firstName": "Bratislava",
    "lastName": "Borjan",
    "email": "bratislava.borjan@example.com",
    "username": "crazyostrich421",
    "password": "karina",
    "invokedAt": "2023-06-03T17:00:41.376Z"
  },
  {
    "firstName": "Embla",
    "lastName": "Wist",
    "email": "embla.wist@example.com",
    "username": "smallpanda508",
    "password": "buffalo",
    "invokedAt": "2023-06-03T18:00:42.495Z"
  },
  {
    "firstName": "Anastasia",
    "lastName": "Lefevre",
    "email": "anastasia.lefevre@example.com",
    "username": "silvercat145",
    "password": "henti",
    "invokedAt": "2023-06-03T19:00:50.880Z"
  },
  {
    "firstName": "Nino",
    "lastName": "Gerard",
    "email": "nino.gerard@example.com",
    "username": "orangeswan443",
    "password": "slayer1",
    "invokedAt": "2023-06-03T20:00:46.513Z"
  },
  {
    "firstName": "Kent",
    "lastName": "Jongerden",
    "email": "kent.jongerden@example.com",
    "username": "yellowrabbit358",
    "password": "5150",
    "invokedAt": "2023-06-03T21:00:42.505Z"
  },
  {
    "firstName": "Handan",
    "lastName": "Groenevelt",
    "email": "handan.groenevelt@example.com",
    "username": "brownpeacock304",
    "password": "haggis",
    "invokedAt": "2023-06-03T22:00:33.296Z"
  }
]