[
  {
    "firstName": "Maxwell",
    "lastName": "Thomas",
    "email": "maxwell.thomas@example.com",
    "username": "orangeelephant319",
    "password": "laura",
    "invokedAt": "2024-02-08T00:00:37.445Z"
  },
  {
    "firstName": "Xavier",
    "lastName": "Knight",
    "email": "xavier.knight@example.com",
    "username": "beautifulmouse402",
    "password": "luna",
    "invokedAt": "2024-02-08T01:20:38.124Z"
  },
  {
    "firstName": "Velizar",
    "lastName": "Bjelica",
    "email": "velizar.bjelica@example.com",
    "username": "heavypeacock391",
    "password": "mischief",
    "invokedAt": "2024-02-08T02:05:07.986Z"
  },
  {
    "firstName": "Elisabeth",
    "lastName": "Becker",
    "email": "elisabeth.becker@example.com",
    "username": "redgoose835",
    "password": "jello",
    "invokedAt": "2024-02-08T03:00:24.143Z"
  }
]