[
  {
    "firstName": "Matas",
    "lastName": "Nyvoll",
    "email": "matas.nyvoll@example.com",
    "username": "greenladybug119",
    "password": "sprite",
    "invokedAt": "2025-12-27T00:00:31.287Z"
  },
  {
    "firstName": "کیمیا",
    "lastName": "گلشن",
    "email": "khymy.glshn@example.com",
    "username": "silverrabbit127",
    "password": "7779311",
    "invokedAt": "2025-12-27T01:28:01.360Z"
  },
  {
    "firstName": "Holly",
    "lastName": "Castillo",
    "email": "holly.castillo@example.com",
    "username": "orangecat705",
    "password": "cruiser",
    "invokedAt": "2025-12-27T02:30:22.754Z"
  },
  {
    "firstName": "Peetu",
    "lastName": "Pakkala",
    "email": "peetu.pakkala@example.com",
    "username": "silverlion174",
    "password": "stephani",
    "invokedAt": "2025-12-27T03:26:40.974Z"
  },
  {
    "firstName": "Mila",
    "lastName": "Stavrum",
    "email": "mila.stavrum@example.com",
    "username": "brownrabbit455",
    "password": "vides",
    "invokedAt": "2025-12-27T04:07:52.382Z"
  },
  {
    "firstName": "Gökhan",
    "lastName": "Tokgöz",
    "email": "gokhan.tokgoz@example.com",
    "username": "crazyostrich181",
    "password": "951753",
    "invokedAt": "2025-12-27T05:00:59.762Z"
  },
  {
    "firstName": "Aaron",
    "lastName": "Sotelo",
    "email": "aaron.sotelo@example.com",
    "username": "yellowfish623",
    "password": "zulu",
    "invokedAt": "2025-12-27T06:00:28.100Z"
  },
  {
    "firstName": "Gaurav",
    "lastName": "Prabhakaran",
    "email": "gaurav.prabhakaran@example.com",
    "username": "heavyduck295",
    "password": "seeking",
    "invokedAt": "2025-12-27T07:00:50.018Z"
  },
  {
    "firstName": "Turbrid",
    "lastName": "Pezhanskiy",
    "email": "turbrid.pezhanskiy@example.com",
    "username": "redbutterfly821",
    "password": "boytoy",
    "invokedAt": "2025-12-27T08:00:27.589Z"
  },
  {
    "firstName": "Mélissa",
    "lastName": "Clement",
    "email": "melissa.clement@example.com",
    "username": "angryswan153",
    "password": "motion",
    "invokedAt": "2025-12-27T09:00:25.656Z"
  },
  {
    "firstName": "Feodora",
    "lastName": "Soldatenko",
    "email": "feodora.soldatenko@example.com",
    "username": "angrywolf507",
    "password": "dalejr",
    "invokedAt": "2025-12-27T10:00:22.687Z"
  },
  {
    "firstName": "Andrés",
    "lastName": "Garrido",
    "email": "andres.garrido@example.com",
    "username": "happydog320",
    "password": "mykids",
    "invokedAt": "2025-12-27T11:00:23.523Z"
  },
  {
    "firstName": "Elijah",
    "lastName": "Alvarez",
    "email": "elijah.alvarez@example.com",
    "username": "lazygorilla169",
    "password": "maxime",
    "invokedAt": "2025-12-27T12:00:29.482Z"
  },
  {
    "firstName": "Khaoula",
    "lastName": "Oudenaarden",
    "email": "khaoula.oudenaarden@example.com",
    "username": "purpleswan378",
    "password": "norris",
    "invokedAt": "2025-12-27T13:08:33.824Z"
  },
  {
    "firstName": "Sergio",
    "lastName": "Pérez",
    "email": "sergio.perez@example.com",
    "username": "sadmeercat155",
    "password": "putter",
    "invokedAt": "2025-12-27T14:00:25.313Z"
  },
  {
    "firstName": "William",
    "lastName": "Christiansen",
    "email": "william.christiansen@example.com",
    "username": "whitewolf167",
    "password": "daphne",
    "invokedAt": "2025-12-27T15:00:20.533Z"
  },
  {
    "firstName": "Iva",
    "lastName": "Obradović",
    "email": "iva.obradovic@example.com",
    "username": "blackladybug697",
    "password": "drowssap",
    "invokedAt": "2025-12-27T16:00:24.761Z"
  }
]