[
  {
    "firstName": "Alexander",
    "lastName": "Sutton",
    "email": "alexander.sutton@example.com",
    "username": "redbear315",
    "password": "letmein",
    "invokedAt": "2025-09-08T00:00:30.163Z"
  },
  {
    "firstName": "Kaïs",
    "lastName": "Michel",
    "email": "kais.michel@example.com",
    "username": "happygorilla615",
    "password": "crow",
    "invokedAt": "2025-09-08T01:27:49.683Z"
  },
  {
    "firstName": "Florus",
    "lastName": "Noorland",
    "email": "florus.noorland@example.com",
    "username": "tinywolf585",
    "password": "swedish",
    "invokedAt": "2025-09-08T02:27:55.270Z"
  },
  {
    "firstName": "Marcus",
    "lastName": "Montgomery",
    "email": "marcus.montgomery@example.com",
    "username": "blacksnake804",
    "password": "dragoon",
    "invokedAt": "2025-09-08T03:16:04.345Z"
  },
  {
    "firstName": "Álvaro",
    "lastName": "Suarez",
    "email": "alvaro.suarez@example.com",
    "username": "bigdog492",
    "password": "sandiego",
    "invokedAt": "2025-09-08T04:00:18.310Z"
  },
  {
    "firstName": "Lincoln",
    "lastName": "Lee",
    "email": "lincoln.lee@example.com",
    "username": "brownmeercat712",
    "password": "angel",
    "invokedAt": "2025-09-08T05:00:23.409Z"
  },
  {
    "firstName": "Joe",
    "lastName": "Hansen",
    "email": "joe.hansen@example.com",
    "username": "tinywolf761",
    "password": "garrett",
    "invokedAt": "2025-09-08T06:00:30.524Z"
  }
]