[
  {
    "firstName": "Sergio",
    "lastName": "Rodríquez",
    "email": "sergio.rodriquez@example.com",
    "username": "silvergoose288",
    "password": "1018",
    "invokedAt": "2025-09-26T00:00:37.754Z"
  },
  {
    "firstName": "Kayla",
    "lastName": "West",
    "email": "kayla.west@example.com",
    "username": "crazybutterfly100",
    "password": "charlie123",
    "invokedAt": "2025-09-26T01:27:40.563Z"
  },
  {
    "firstName": "Dag",
    "lastName": "Nesheim",
    "email": "dag.nesheim@example.com",
    "username": "organicbear890",
    "password": "mingus",
    "invokedAt": "2025-09-26T02:25:26.804Z"
  },
  {
    "firstName": "Marcus",
    "lastName": "Walker",
    "email": "marcus.walker@example.com",
    "username": "bigladybug745",
    "password": "benton",
    "invokedAt": "2025-09-26T03:12:02.383Z"
  },
  {
    "firstName": "Kirilo",
    "lastName": "Zinkivskiy",
    "email": "kirilo.zinkivskiy@example.com",
    "username": "bigsnake427",
    "password": "megapass",
    "invokedAt": "2025-09-26T04:00:24.744Z"
  },
  {
    "firstName": "Oscar",
    "lastName": "Christensen",
    "email": "oscar.christensen@example.com",
    "username": "tinycat520",
    "password": "tempest",
    "invokedAt": "2025-09-26T05:00:29.498Z"
  }
]