[
  {
    "firstName": "Gabriel",
    "lastName": "Colin",
    "email": "gabriel.colin@example.com",
    "username": "bigleopard956",
    "password": "wildfire",
    "invokedAt": "2026-04-05T00:03:31.123Z"
  },
  {
    "firstName": "آوین",
    "lastName": "رضایی",
    "email": "awyn.rdyy@example.com",
    "username": "purpleduck512",
    "password": "berkeley",
    "invokedAt": "2026-04-05T01:29:40.629Z"
  },
  {
    "firstName": "August",
    "lastName": "Poulsen",
    "email": "august.poulsen@example.com",
    "username": "purplefrog443",
    "password": "dizzy",
    "invokedAt": "2026-04-05T02:57:07.421Z"
  },
  {
    "firstName": "Renato",
    "lastName": "Riviere",
    "email": "renato.riviere@example.com",
    "username": "purplepeacock980",
    "password": "roberto",
    "invokedAt": "2026-04-05T04:00:11.267Z"
  },
  {
    "firstName": "Sophia",
    "lastName": "Lopez",
    "email": "sophia.lopez@example.com",
    "username": "ticklishfrog634",
    "password": "mouse1",
    "invokedAt": "2026-04-05T04:57:03.408Z"
  },
  {
    "firstName": "Mark",
    "lastName": "Weaver",
    "email": "mark.weaver@example.com",
    "username": "beautifullion100",
    "password": "beckham",
    "invokedAt": "2026-04-05T05:34:20.075Z"
  },
  {
    "firstName": "Lino",
    "lastName": "Henry",
    "email": "lino.henry@example.com",
    "username": "orangepanda314",
    "password": "pharao",
    "invokedAt": "2026-04-05T06:19:48.602Z"
  }
]